{"value":{"swimmers":[{"rank":"1","name":"Thomas Rickels","time":"16:50.22","date":"19/07/25","club":"Co Liverpool","tiref":"1402615"},{"rank":"2","name":"Archie McGuire","time":"16:55.48","date":"19/07/25","club":"Co Sund'land","tiref":"1333803"},{"rank":"3","name":"Jacson Crabb","time":"16:55.89","date":"19/07/25","club":"Co Leicester","tiref":"1478601"},{"rank":"4","name":"Ethan Knights","time":"17:06.23","date":"18/01/26","club":"teamipswich","tiref":"1642175"},{"rank":"5","name":"Aaron Cain","time":"17:16.28","date":"25/01/26","club":"Wycombe Dist","tiref":"1469826"},{"rank":"6","name":"Joshua Hutchinson","time":"17:16.68","date":"24/01/26","club":"Woking","tiref":"1393523"},{"rank":"7","name":"Finlay Byrne","time":"17:26.15","date":"19/07/25","club":"Co Liverpool","tiref":"1505209"},{"rank":"8","name":"Perrin Ma","time":"17:32.72","date":"30/07/25","club":"Hatfield","tiref":"1595627"},{"rank":"9","name":"Archie Ainslie","time":"17:33.95","date":"26/04/25","club":"Co Sheffield","tiref":"1406040"},{"rank":"10","name":"Finn Hemmant","time":"17:36.16","date":"19/07/25","club":"Reading","tiref":"1522342"},{"rank":"11","name":"Tom Holt","time":"17:37.48","date":"26/04/25","club":"Co Sund'land","tiref":"1478353"},{"rank":"12","name":"Lewis Hall","time":"17:37.73","date":"26/04/25","club":"KingstonHull","tiref":"1369978"},{"rank":"13","name":"Zachary Maiden","time":"17:40.41","date":"18/01/26","club":"Beau Sejour","tiref":"1520242"},{"rank":"14","name":"Jeffrey Lange","time":"17:41.48","date":"12/12/25","club":"Co Leeds","tiref":"1669148"},{"rank":"15","name":"Xavier Zerban","time":"17:44.09","date":"24/01/26","club":"Biggleswade","tiref":"1491940"},{"rank":"16","name":"Daniel Tew","time":"17:44.86","date":"30/07/25","club":"York City","tiref":"1476946"},{"rank":"17","name":"Harry Osborne","time":"17:45.84","date":"30/07/25","club":"Co Sheffield","tiref":"1489134"},{"rank":"18","name":"Noah Darnell","time":"17:46.78","date":"11/04/25","club":"Co Leeds","tiref":"1524610"},{"rank":"19","name":"Henry Barker","time":"17:47.36","date":"18/01/26","club":"Co South'ton","tiref":"1474815"},{"rank":"20","name":"Jack Militis","time":"17:47.51","date":"26/04/25","club":"TigersJersey","tiref":"966843"},{"rank":"21","name":"Joshua Kicks","time":"17:49.22","date":"26/04/25","club":"Killerwhales","tiref":"1523234"},{"rank":"22","name":"George Harrison","time":"17:50.22","date":"30/07/25","club":"KingstonHull","tiref":"1370018"},{"rank":"23","name":"Stefan Grant","time":"17:52.86","date":"13/12/25","club":"Grantham","tiref":"1590550"},{"rank":"24","name":"Rory Burnell","time":"17:54.44","date":"21/03/25","club":"Street","tiref":"1600222"},{"rank":"25","name":"Edward McDonald","time":"17:54.71","date":"13/12/25","club":"Warrington W","tiref":"1415564"},{"rank":"26","name":"Tait Shillingford","time":"17:55.50","date":"30/07/25","club":"Royal Wolv","tiref":"1403680"},{"rank":"27","name":"Charlie Braid","time":"17:56.50","date":"26/04/25","club":"Bromley","tiref":"1578201"},{"rank":"28","name":"Joshua O’donnell","time":"17:57.42","date":"24/01/26","club":"Wandsworth","tiref":"1514679"},{"rank":"29","name":"James Graham","time":"17:57.78","date":"30/07/25","club":"Co Liverpool","tiref":"1326259"},{"rank":"30","name":"Harry Willis","time":"17:59.73","date":"30/07/25","club":"Newcastle","tiref":"1387018"},{"rank":"31","name":"Gus Fraser","time":"18:00.98","date":"30/07/25","club":"Winsford","tiref":"1497346"},{"rank":"32","name":"Ignacy Krzemien-Piechota","time":"18:04.06","date":"24/01/26","club":"Wandsworth","tiref":"1631474"},{"rank":"33","name":"Jacob Irving","time":"18:04.20","date":"09/05/25","club":"Co Liverpool","tiref":"1421053"},{"rank":"34","name":"Kais Alhijazi","time":"18:06.18","date":"30/07/25","club":"Co Leicester","tiref":"1423582"},{"rank":"35","name":"Thomas Fenwick","time":"18:12.39","date":"30/07/25","club":"Hatfield","tiref":"1486193"},{"rank":"36","name":"William Royston","time":"18:12.74","date":"18/01/26","club":"Fareham N'ds","tiref":"1599827"},{"rank":"37","name":"Michael Gubars","time":"18:13.61","date":"24/01/26","club":"Guildford Ct","tiref":"1388896"},{"rank":"38","name":"Flynn Clark","time":"18:13.70","date":"01/02/26","club":"Derby Excel","tiref":"1326828"},{"rank":"39","name":"Oliver Barrett","time":"18:15.40","date":"26/04/25","club":"Harrogate","tiref":"1524648"},{"rank":"40","name":"Alfie Craggs","time":"18:15.70","date":"12/12/25","club":"Co Leeds","tiref":"1587886"},{"rank":"41","name":"Seth Charlesworth","time":"18:16.10","date":"11/04/25","club":"Co Sheffield","tiref":"1437149"},{"rank":"42","name":"Oscar O'Donnell","time":"18:16.14","date":"26/04/25","club":"Co Leeds","tiref":"1501618"},{"rank":"43","name":"Henry Bolton","time":"18:16.17","date":"18/01/26","club":"Beau Sejour","tiref":"1678334"},{"rank":"44","name":"Arlo Hems Gillson","time":"18:16.75","date":"01/02/26","club":"Repton","tiref":"1473860"},{"rank":"45","name":"Olaf Grudowski","time":"18:18.43","date":"26/04/25","club":"Co Leeds","tiref":"1628154"},{"rank":"46","name":"Lorcan Wolton","time":"18:20.22","date":"21/03/25","club":"Co Bristol","tiref":"1476412"},{"rank":"47","name":"Oliver Sigley","time":"18:21.73","date":"27/04/25","club":"Mt Kelly","tiref":"1452165"},{"rank":"48","name":"Arlo Shaw","time":"18:22.12","date":"26/04/25","club":"Bromley","tiref":"1609288"},{"rank":"49","name":"Toby Drayson","time":"18:22.64","date":"09/03/25","club":"BelperMarlin","tiref":"1443616"},{"rank":"50","name":"Oliver Atha","time":"18:23.21","date":"26/04/25","club":"Co Leeds","tiref":"1648157"}],"url":"https://www.swimmingresults.org/12months/last12.php?Pool=L&Stroke=6&Sex=M&AgeGroup=14&date=31%2F01%2F2026&StartNumber=1&RecordsToView=50&Level=N&TargetNationality=E&TargetRegion=P&TargetCounty=XXXX&TargetClub=XXXX"},"expiresAt":1770130291098}