{"value":{"swimmers":[{"rank":"1","name":"Charlie Phipps","time":"4:54.56","date":"24/01/26","club":"Millfield","tiref":"1589213"},{"rank":"2","name":"Lorcan Wolton","time":"4:57.11","date":"22/07/25","club":"Co Bristol","tiref":"1476412"},{"rank":"3","name":"Daniel Lawrence","time":"5:00.04","date":"22/07/25","club":"Guildford Ct","tiref":"1579485"},{"rank":"4","name":"Lewis Hall","time":"5:03.11","date":"31/07/25","club":"KingstonHull","tiref":"1369978"},{"rank":"5","name":"Maxwell Burdett","time":"5:03.23","date":"22/07/25","club":"Co Leicester","tiref":"1450073"},{"rank":"6","name":"Tom Holt","time":"5:04.06","date":"24/01/26","club":"Co Sund'land","tiref":"1478353"},{"rank":"7","name":"Jason Li","time":"5:04.64","date":"22/07/25","club":"Co Birm'ham","tiref":"1367904"},{"rank":"8","name":"Finlay Byrne","time":"5:04.85","date":"22/07/25","club":"Co Liverpool","tiref":"1505209"},{"rank":"9","name":"Mihailo Vuckovic","time":"5:04.89","date":"14/12/25","club":"Ealing","tiref":"1473791"},{"rank":"10","name":"Leo Craven","time":"5:08.59","date":"21/12/25","club":"Warrington W","tiref":"1474547"},{"rank":"11","name":"Leo Ashcroft","time":"5:08.60","date":"31/07/25","club":"Wigan BEST","tiref":"1598809"},{"rank":"12","name":"Francesco Monaco","time":"5:09.20","date":"31/07/25","club":"South Lincs","tiref":"1423652"},{"rank":"13","name":"Noah Willer","time":"5:09.66","date":"18/01/26","club":"Bo Waltham F","tiref":"1491556"},{"rank":"14","name":"Marek Pillay","time":"5:10.33","date":"10/01/26","club":"Co Sheffield","tiref":"1665066"},{"rank":"15","name":"Takara Hasegawa-York","time":"5:10.41","date":"23/11/25","club":"Woking","tiref":"1433946"},{"rank":"16","name":"Jensen Hughes","time":"5:12.89","date":"10/01/26","club":"Co Sheffield","tiref":"1483405"},{"rank":"17","name":"Joshua Kicks","time":"5:12.91","date":"18/01/26","club":"Killerwhales","tiref":"1523234"},{"rank":"18","name":"Kais Alhijazi","time":"5:13.42","date":"20/12/25","club":"Co Leicester","tiref":"1423582"},{"rank":"19","name":"George Beardsmore","time":"5:14.57","date":"01/02/26","club":"Black Lion","tiref":"1501273"},{"rank":"20","name":"Angus Young","time":"5:14.62","date":"13/07/25","club":"Co Leeds","tiref":"1502795"},{"rank":"21","name":"Edward Gregory","time":"5:14.76","date":"04/05/25","club":"Repton","tiref":"1443392"},{"rank":"22","name":"Aidan Jarvis","time":"5:15.22","date":"17/01/26","club":"TigersJersey","tiref":"1469702"},{"rank":"23","name":"Wiktor Gora","time":"5:15.33","date":"31/07/25","club":"Scarborough","tiref":"1649733"},{"rank":"24","name":"James Peters","time":"5:16.82","date":"18/01/26","club":"Basildon Ph","tiref":"1431642"},{"rank":"25","name":"Alex Freeman","time":"5:17.31","date":"21/06/25","club":"Morpeth","tiref":"1362624"},{"rank":"","name":"Oliver Hall","time":"5:17.31","date":"29/11/25","club":"Basingstoke","tiref":"1609666"},{"rank":"27","name":"Sean Mooney","time":"5:17.34","date":"18/01/26","club":"Killerwhales","tiref":"1590804"},{"rank":"28","name":"Oliver Atha","time":"5:17.59","date":"13/12/25","club":"Co Leeds","tiref":"1648157"},{"rank":"29","name":"Edward Rose","time":"5:17.81","date":"31/07/25","club":"Rotherham Mo","tiref":"1518781"},{"rank":"30","name":"Finley Wilkes","time":"5:18.29","date":"18/01/26","club":"Nova Cent'n","tiref":"1483210"},{"rank":"31","name":"Gabriel Barnett","time":"5:18.93","date":"06/04/25","club":"Blackpool Aq","tiref":"1519045"},{"rank":"32","name":"Henry Liddle","time":"5:19.19","date":"24/01/26","club":"AJ Newcastle","tiref":"1609918"},{"rank":"33","name":"Byron Miller","time":"5:19.28","date":"18/01/26","club":"Colchester","tiref":"1603374"},{"rank":"34","name":"James Freeman","time":"5:19.34","date":"26/04/25","club":"TauntonDeane","tiref":"1450481"},{"rank":"35","name":"Lucas Vermaat","time":"5:19.52","date":"10/01/26","club":"Camden Swiss","tiref":"1513504"},{"rank":"36","name":"William Browne","time":"5:19.57","date":"18/04/25","club":"Guildford Ct","tiref":"1604773"},{"rank":"37","name":"Chayton Ho","time":"5:19.80","date":"20/04/25","club":"Camden Swiss","tiref":"1656421"},{"rank":"38","name":"Ashton Hunter","time":"5:20.29","date":"10/01/26","club":"Co Peterboro","tiref":"1595559"},{"rank":"39","name":"Mark Liacas","time":"5:21.40","date":"31/07/25","club":"Hillingdon","tiref":"1595466"},{"rank":"40","name":"Finley Burford","time":"5:21.42","date":"18/01/26","club":"Basildon Ph","tiref":"1431130"},{"rank":"41","name":"Heath Murphy","time":"5:21.88","date":"05/05/25","club":"Nuneaton","tiref":"1582612"},{"rank":"","name":"James Dixon","time":"5:21.88","date":"20/09/25","club":"Co Liverpool","tiref":"1421044"},{"rank":"43","name":"Bertie Woodward","time":"5:22.25","date":"03/01/26","club":"Beacon","tiref":"1577679"},{"rank":"44","name":"Gabriel Marsh","time":"5:22.52","date":"01/02/26","club":"RTW Monson","tiref":"1689087"},{"rank":"45","name":"Oscar Maddrell","time":"5:22.92","date":"31/07/25","club":"Io Man","tiref":"1529095"},{"rank":"46","name":"Harry Callaghan-Wetton","time":"5:22.96","date":"31/07/25","club":"Nova Cent'n","tiref":"1579741"},{"rank":"47","name":"Milton Xavier Yau","time":"5:23.53","date":"05/05/25","club":"Evesham","tiref":"1622039"},{"rank":"","name":"Edward McDonald","time":"5:23.53","date":"21/12/25","club":"Warrington W","tiref":"1415564"},{"rank":"49","name":"Mark Kiraly","time":"5:24.10","date":"18/01/26","club":"Nova Cent'n","tiref":"1523073"},{"rank":"50","name":"Harry Glanville","time":"5:24.57","date":"24/01/26","club":"TauntonDeane","tiref":"1525148"}],"url":"https://www.swimmingresults.org/12months/last12.php?Pool=L&Stroke=17&Sex=M&AgeGroup=13&date=31%2F07%2F2025&StartNumber=1&RecordsToView=50&Level=N&TargetNationality=E&TargetRegion=P&TargetCounty=XXXX&TargetClub=XXXX"},"expiresAt":1770131174792}