{"value":{"swimmers":[{"rank":"1","name":"Abbie Roscoe","time":"4:47.07","date":"24/07/25","club":"Wirral Metro","tiref":"1410384"},{"rank":"2","name":"Ines Guimond-Beetham","time":"4:48.84","date":"24/07/25","club":"Camden Swiss","tiref":"1377383"},{"rank":"3","name":"Katie Lee","time":"4:49.12","date":"08/02/25","club":"Co Salford","tiref":"1367056"},{"rank":"4","name":"Matilda Potter","time":"4:49.46","date":"16/04/25","club":"Co Leeds","tiref":"1455926"},{"rank":"5","name":"Amelie Blocksidge","time":"4:51.21","date":"08/02/25","club":"Co Salford","tiref":"1290582"},{"rank":"6","name":"Petra Varga","time":"4:54.41","date":"16/04/25","club":"Wirral Metro","tiref":"1414718"},{"rank":"7","name":"Annabel Cooke","time":"5:00.28","date":"16/04/25","club":"Co Sheffield","tiref":"1357810"},{"rank":"8","name":"Millie Threlfall","time":"5:00.32","date":"24/07/25","club":"Co Leeds","tiref":"1410499"},{"rank":"9","name":"Hollie Whaymand","time":"5:00.50","date":"16/04/25","club":"Repton","tiref":"1170125"},{"rank":"10","name":"Darcie Platts","time":"5:01.76","date":"24/07/25","club":"Co Leicester","tiref":"1260823"},{"rank":"11","name":"Willow Harrison","time":"5:02.80","date":"24/07/25","club":"Co Sheffield","tiref":"1426011"},{"rank":"12","name":"Amber Rigg","time":"5:04.22","date":"11/05/25","club":"Dumfries","tiref":"1369064"},{"rank":"13","name":"Gabrielle Freeman","time":"5:04.65","date":"03/05/25","club":"Morpeth","tiref":"1314203"},{"rank":"14","name":"Sophie King","time":"5:04.69","date":"03/05/25","club":"Mt Kelly","tiref":"1164424"},{"rank":"15","name":"Martyna Karabacz","time":"5:05.88","date":"11/01/26","club":"Camden Swiss","tiref":"1334797"},{"rank":"16","name":"Evie Cutter","time":"5:06.63","date":"24/07/25","club":"Wigan","tiref":"1361965"},{"rank":"17","name":"Sadie Hunter","time":"5:08.04","date":"11/01/26","club":"Co Peterboro","tiref":"1102124"},{"rank":"18","name":"Chloe Barnard","time":"5:08.27","date":"15/03/25","club":"Basildon Ph","tiref":"1319829"},{"rank":"19","name":"Darcey Crossley","time":"5:08.40","date":"16/04/25","club":"Co Leeds","tiref":"1339557"},{"rank":"20","name":"Lily Horton","time":"5:08.44","date":"23/03/25","club":"Wirral Metro","tiref":"1377070"},{"rank":"21","name":"Ella Smith","time":"5:08.56","date":"03/05/25","club":"Bo Stockton","tiref":"1315041"},{"rank":"22","name":"Evelyn Hallissey","time":"5:08.94","date":"03/05/25","club":"Newcastle","tiref":"1360016"},{"rank":"23","name":"Mia Hughes","time":"5:09.56","date":"31/01/26","club":"Bromley","tiref":"1245512"},{"rank":"24","name":"Katy Wun","time":"5:10.41","date":"26/04/25","club":"Camden Swiss","tiref":"1426580"},{"rank":"25","name":"Annie McLeod","time":"5:10.92","date":"29/07/25","club":"Putteridge","tiref":"1254221"},{"rank":"26","name":"Alana Maddock","time":"5:11.82","date":"22/11/25","club":"Eastleigh","tiref":"1396366"},{"rank":"27","name":"Ever Ives","time":"5:12.20","date":"09/03/25","club":"Hatfield","tiref":"1380105"},{"rank":"28","name":"Danica Forster","time":"5:12.78","date":"29/07/25","club":"Wycombe Dist","tiref":"1414202"},{"rank":"29","name":"Grace Macdonald","time":"5:13.46","date":"29/07/25","club":"Grantham","tiref":"1441022"},{"rank":"30","name":"Ischia Howells","time":"5:13.61","date":"13/01/26","club":"Gloucester","tiref":"1311856"},{"rank":"31","name":"Isabel Handley","time":"5:15.08","date":"16/03/25","club":"Co Leeds","tiref":"1421134"},{"rank":"32","name":"Hannah Finney","time":"5:15.46","date":"02/03/25","club":"Cosacss","tiref":"1366491"},{"rank":"33","name":"Maddison Notley","time":"5:18.21","date":"14/03/25","club":"MwayMaritime","tiref":"1341096"},{"rank":"34","name":"Jessica Oxley","time":"5:19.33","date":"25/01/26","club":"Co Leicester","tiref":"1325180"},{"rank":"35","name":"Eloise Herbert","time":"5:19.54","date":"12/01/26","club":"Mt Kelly","tiref":"1438352"},{"rank":"36","name":"Charlotte Heyden","time":"5:19.74","date":"07/03/25","club":"Staines","tiref":"1378941"},{"rank":"37","name":"Layla Richmond","time":"5:20.43","date":"06/04/25","club":"Maxwell","tiref":"1381920"},{"rank":"38","name":"Rylie Ackroyd","time":"5:20.80","date":"08/02/25","club":"Mt Kelly","tiref":"1453805"},{"rank":"39","name":"Charlotte Callaghan-Wetton","time":"5:20.85","date":"10/05/25","club":"Nova Cent'n","tiref":"1332969"},{"rank":"40","name":"Abigail Needs","time":"5:21.03","date":"06/04/25","club":"Exeter City","tiref":"1297000"},{"rank":"41","name":"Isabel Owen","time":"5:21.08","date":"03/05/25","club":"Sandwell","tiref":"1353819"},{"rank":"42","name":"Olexa Miles","time":"5:21.87","date":"07/03/25","club":"Thanet Swim","tiref":"1244370"},{"rank":"43","name":"Cazia Martin","time":"5:22.93","date":"03/05/25","club":"Co Sheffield","tiref":"1350340"},{"rank":"44","name":"Lauren Cox","time":"5:23.13","date":"02/03/25","club":"Newcastle St","tiref":"1432224"},{"rank":"45","name":"Rosie Pope","time":"5:23.35","date":"31/01/26","club":"Thanet Swim","tiref":"1328788"},{"rank":"46","name":"Sienna Ramery","time":"5:23.48","date":"20/04/25","club":"Wycombe Dist","tiref":"1303303"},{"rank":"47","name":"Maryse Magnee","time":"5:23.64","date":"03/05/25","club":"Sandwell","tiref":"1576097"},{"rank":"48","name":"Madeleine Hind","time":"5:23.68","date":"05/05/25","club":"RTW Monson","tiref":"1350038"},{"rank":"49","name":"Ilana Nightingale-Ellis","time":"5:23.71","date":"09/03/25","club":"RTW Monson","tiref":"1392919"},{"rank":"50","name":"Millie Linton","time":"5:23.75","date":"25/01/26","club":"Bo Stockton","tiref":"1304841"}],"url":"https://www.swimmingresults.org/12months/last12.php?Pool=L&Stroke=17&Sex=F&AgeGroup=16&date=31%2F07%2F2025&StartNumber=1&RecordsToView=50&Level=N&TargetNationality=E&TargetRegion=P&TargetCounty=XXXX&TargetClub=XXXX"},"expiresAt":1770131202579}