{"value":{"swimmers":[{"rank":"1","name":"Gabrielle Idle-Beavers","time":"31.63","date":"20/07/25","club":"Mt Kelly","tiref":"1290149"},{"rank":"2","name":"Anna Finlay","time":"32.62","date":"20/07/25","club":"Derwent&Gate","tiref":"1324776"},{"rank":"3","name":"Danielle Siong","time":"32.79","date":"15/04/25","club":"Co Milton K","tiref":"1318287"},{"rank":"4","name":"Gabriella Hunt","time":"33.03","date":"20/07/25","club":"Co Liverpool","tiref":"1322890"},{"rank":"5","name":"Millie Harris","time":"33.14","date":"02/08/25","club":"West Norfolk","tiref":"1352059"},{"rank":"6","name":"Ella Greatbatch","time":"33.35","date":"09/03/25","club":"Bishop Stort","tiref":"1258466"},{"rank":"7","name":"Rose Harrison","time":"33.73","date":"13/01/26","club":"Tiverton","tiref":"1403330"},{"rank":"8","name":"Scarlett Davie","time":"33.81","date":"24/01/26","club":"RTW Monson","tiref":"1332348"},{"rank":"9","name":"Poppy Williams","time":"33.92","date":"03/05/25","club":"Swindon Dolp","tiref":"1289705"},{"rank":"10","name":"Amelia Murphy","time":"34.13","date":"20/07/25","club":"Witham Dolph","tiref":"1420237"},{"rank":"11","name":"Grace Ryder","time":"34.33","date":"03/05/25","club":"Worcester","tiref":"1325944"},{"rank":"12","name":"Georgina Hamilton","time":"34.42","date":"20/07/25","club":"Co St Albans","tiref":"1327430"},{"rank":"13","name":"Amber Valletta","time":"34.43","date":"15/02/25","club":"Walsall","tiref":"1372896"},{"rank":"14","name":"Amelie Brind","time":"34.44","date":"05/05/25","club":"Havant & Wat","tiref":"1299088"},{"rank":"15","name":"Mabel Walker","time":"34.46","date":"15/04/25","club":"Birm'ham Uni","tiref":"1241929"},{"rank":"16","name":"Elisha D'Souza","time":"34.55","date":"09/02/25","club":"Hillingdon","tiref":"1431404"},{"rank":"17","name":"Ellen Eccleston","time":"34.57","date":"02/08/25","club":"Co Norwich","tiref":"1347066"},{"rank":"18","name":"Lexie O'Connor","time":"34.66","date":"18/01/26","club":"Basildon Ph","tiref":"1246039"},{"rank":"19","name":"Isobel Muncaster","time":"34.67","date":"05/05/25","club":"Seaclose","tiref":"1590252"},{"rank":"20","name":"Sophie Reh","time":"34.68","date":"20/07/25","club":"Co Coventry","tiref":"1291967"},{"rank":"21","name":"Isla Hamilton","time":"34.86","date":"02/08/25","club":"Norwich Swan","tiref":"1362132"},{"rank":"","name":"Emilia Oliver","time":"34.86","date":"24/01/26","club":"RTW Monson","tiref":"1396990"},{"rank":"23","name":"Rachael Carpenter","time":"34.88","date":"03/05/25","club":"Ware","tiref":"1188458"},{"rank":"24","name":"Lily Hunt","time":"35.04","date":"03/05/25","club":"Swindon Dolp","tiref":"1278590"},{"rank":"25","name":"Lilly Davis","time":"35.05","date":"03/05/25","club":"Co Peterboro","tiref":"1199099"},{"rank":"26","name":"Maisie Brown","time":"35.06","date":"20/07/25","club":"Rushmoor Ryl","tiref":"1427009"},{"rank":"27","name":"Gracie Parker","time":"35.12","date":"09/03/25","club":"Basildon Ph","tiref":"1207297"},{"rank":"28","name":"Brecon Westwood","time":"35.13","date":"15/03/25","club":"Worcester","tiref":"1199390"},{"rank":"29","name":"Lucy Shore","time":"35.16","date":"11/05/25","club":"Crewe Flyers","tiref":"1342384"},{"rank":"30","name":"Libby Buckby","time":"35.19","date":"02/08/25","club":"Nova Cent'n","tiref":"1598058"},{"rank":"31","name":"Esme Stringer","time":"35.22","date":"09/03/25","club":"Bishop Stort","tiref":"1117685"},{"rank":"32","name":"Faith Dunn","time":"35.44","date":"03/05/25","club":"Shrewsbury","tiref":"1501573"},{"rank":"33","name":"Olivia Anstey","time":"35.45","date":"01/03/25","club":"Louth","tiref":"1249488"},{"rank":"34","name":"Mabel Robertson","time":"35.46","date":"09/03/25","club":"Co Sheffield","tiref":"1368937"},{"rank":"35","name":"Charlotte Cope","time":"35.47","date":"23/01/26","club":"Guildford Ct","tiref":"1255397"},{"rank":"36","name":"Niamh Savory","time":"35.53","date":"20/07/25","club":"Newcastle","tiref":"1232149"},{"rank":"37","name":"Elizabeth Wright","time":"35.55","date":"22/03/25","club":"Co Sheffield","tiref":"1250627"},{"rank":"38","name":"Olivia Dunn","time":"35.59","date":"03/05/25","club":"Mt Kelly","tiref":"1359600"},{"rank":"39","name":"Zara Roberts","time":"35.64","date":"10/01/26","club":"Tilehurst","tiref":"1606693"},{"rank":"40","name":"Orla Evans","time":"35.72","date":"08/02/25","club":"Crawley","tiref":"1343907"},{"rank":"41","name":"Heidi Walkin","time":"35.75","date":"08/03/25","club":"Thanet Swim","tiref":"1385466"},{"rank":"","name":"Lily Cobble","time":"35.75","date":"03/05/25","club":"Co Coventry","tiref":"1389187"},{"rank":"","name":"Hazel-Anne Carter","time":"35.75","date":"05/05/25","club":"Wycombe Dist","tiref":"1288250"},{"rank":"44","name":"Ruby Chudleigh","time":"35.77","date":"22/03/25","club":"Sandwell","tiref":"1237154"},{"rank":"45","name":"Grace Wingham","time":"35.79","date":"27/04/25","club":"Corby","tiref":"1319265"},{"rank":"46","name":"Holly Hopwood","time":"35.80","date":"23/03/25","club":"Guildford Ct","tiref":"1174537"},{"rank":"47","name":"Rebecca McCoubrie","time":"35.83","date":"03/05/25","club":"Gloucester","tiref":"1241046"},{"rank":"","name":"India Washer","time":"35.83","date":"05/05/25","club":"Wycombe Dist","tiref":"1248119"},{"rank":"49","name":"Rose Keefe","time":"35.86","date":"05/05/25","club":"Co Wakefield","tiref":"1263732"},{"rank":"50","name":"Louisa Pollard","time":"35.88","date":"05/05/25","club":"Dover Life","tiref":"1248578"}],"url":"https://www.swimmingresults.org/12months/last12.php?Pool=L&Stroke=7&Sex=F&AgeGroup=17&date=30%2F06%2F2025&StartNumber=1&RecordsToView=50&Level=N&TargetNationality=E&TargetRegion=P&TargetCounty=XXXX&TargetClub=XXXX"},"expiresAt":1770130361667}