{"value":{"swimmers":[{"rank":"1","name":"Ethan Kelly","time":"15:44.68","date":"17/04/25","club":"Co Liverpool","tiref":"1407510"},{"rank":"2","name":"Joshua Keogh","time":"16:10.21","date":"19/07/25","club":"Bolton Metro","tiref":"1273239"},{"rank":"3","name":"George Daintith","time":"16:14.57","date":"19/07/25","club":"Co Liverpool","tiref":"1328780"},{"rank":"4","name":"Harry Cocks","time":"16:14.95","date":"19/07/25","club":"Thanet Swim","tiref":"1304176"},{"rank":"5","name":"Tom Belt","time":"16:16.10","date":"19/07/25","club":"Mt Kelly","tiref":"1284537"},{"rank":"6","name":"Elliot Lawton","time":"16:17.71","date":"17/04/25","club":"Co Coventry","tiref":"1422344"},{"rank":"7","name":"Hugh Mason-Williams","time":"16:20.27","date":"19/07/25","club":"Co Birm'ham","tiref":"1341881"},{"rank":"8","name":"Benjamin Ross","time":"16:29.19","date":"08/02/25","club":"Co Salford","tiref":"1195904"},{"rank":"9","name":"Dylan Madican","time":"16:37.53","date":"19/07/25","club":"Co Liverpool","tiref":"1468986"},{"rank":"10","name":"Thomas Jennings","time":"16:39.49","date":"17/04/25","club":"Portsmouth N","tiref":"1383271"},{"rank":"11","name":"Robert Fenner","time":"16:40.61","date":"30/07/25","club":"Basildon Ph","tiref":"1334490"},{"rank":"12","name":"Joseph Hall","time":"16:44.12","date":"03/05/25","club":"Co Leeds","tiref":"1381840"},{"rank":"13","name":"Aidan Kearney","time":"16:44.24","date":"19/07/25","club":"Co Liverpool","tiref":"1399896"},{"rank":"14","name":"Josh Miles","time":"16:45.45","date":"27/04/25","club":"Bristol&SGlo","tiref":"1345445"},{"rank":"15","name":"Adam O'Neal","time":"16:50.96","date":"30/07/25","club":"Bedford SS","tiref":"1396648"},{"rank":"16","name":"Sam Wright","time":"16:53.79","date":"09/02/25","club":"Tadcaster","tiref":"1438348"},{"rank":"17","name":"Jai Diddee","time":"16:56.24","date":"11/04/25","club":"Tynemouth","tiref":"1324102"},{"rank":"18","name":"Michael O'Neill","time":"17:00.37","date":"23/01/26","club":"Bo Stockton","tiref":"1371034"},{"rank":"19","name":"Lucas Galant Draysey","time":"17:03.12","date":"30/07/25","club":"Mt Kelly","tiref":"1442119"},{"rank":"20","name":"Daniel Belsey","time":"17:07.36","date":"16/03/25","club":"Hatfield","tiref":"1281277"},{"rank":"21","name":"Rufus Parry","time":"17:14.26","date":"04/05/25","club":"Wycombe Dist","tiref":"1316947"},{"rank":"22","name":"George Carter","time":"17:14.38","date":"30/07/25","club":"Co Cambridge","tiref":"1292835"},{"rank":"23","name":"Griffin Thomas","time":"17:23.47","date":"18/01/26","club":"Winchester","tiref":"945453"},{"rank":"24","name":"Archie Turner","time":"17:24.14","date":"06/04/25","club":"Basingstoke","tiref":"1210016"},{"rank":"25","name":"Oliver Ingham","time":"17:30.50","date":"11/04/25","club":"Co Salford","tiref":"1395544"},{"rank":"26","name":"Oscar Townsend","time":"17:31.40","date":"03/05/25","club":"Ledbury","tiref":"1493424"},{"rank":"27","name":"Brandon Macdonald-Williams","time":"17:35.69","date":"10/05/25","club":"Bishop Stort","tiref":"1299521"},{"rank":"28","name":"Zachary Powell","time":"17:36.04","date":"08/02/25","club":"TauntonDeane","tiref":"1338111"},{"rank":"29","name":"Ethan Wills","time":"17:38.02","date":"04/05/25","club":"Wycombe Dist","tiref":"1329447"},{"rank":"30","name":"Matthew James","time":"17:40.23","date":"11/04/25","club":"Co Leeds","tiref":"1380169"},{"rank":"31","name":"Arthur Owens","time":"17:40.63","date":"09/02/25","club":"Co Leeds","tiref":"1458395"},{"rank":"32","name":"Ivan Gallagher","time":"17:45.38","date":"03/05/25","club":"Derwent&Gate","tiref":"1467889"},{"rank":"33","name":"Joshua Allinson-Rodrigues","time":"17:45.84","date":"10/05/25","club":"Teddington","tiref":"1477407"},{"rank":"34","name":"Jed Millin","time":"17:46.13","date":"18/01/26","club":"Stowmarket","tiref":"1414573"},{"rank":"35","name":"Luke Drew","time":"17:46.74","date":"24/01/26","club":"Guildford Ct","tiref":"1342411"},{"rank":"36","name":"Daniel Williams","time":"17:49.72","date":"11/03/25","club":"Hatfield","tiref":"1319596"},{"rank":"37","name":"Noah Kendrick","time":"17:49.83","date":"10/05/25","club":"Co B'ton & H","tiref":"1229366"},{"rank":"38","name":"James Fothergill","time":"17:57.15","date":"23/03/25","club":"Co Manch Aq","tiref":"1403589"},{"rank":"39","name":"Alfie Charlton","time":"18:00.69","date":"09/02/25","club":"Millfield","tiref":"1374727"},{"rank":"40","name":"Finn Jackson","time":"18:02.01","date":"01/03/25","club":"Maidstone SC","tiref":"1347240"},{"rank":"41","name":"Dylan Jamieson","time":"18:02.44","date":"13/04/25","club":"Derby Excel","tiref":"1412315"},{"rank":"42","name":"Harley Williams","time":"18:04.55","date":"16/02/25","club":"Hastings","tiref":"983564"},{"rank":"43","name":"Lawrence Chapman","time":"18:05.99","date":"22/02/25","club":"Worksop","tiref":"1348611"},{"rank":"44","name":"Oliver Nutter","time":"18:10.14","date":"08/02/25","club":"Burnley BOBC","tiref":"1376109"},{"rank":"45","name":"George Pigott","time":"18:11.50","date":"06/04/25","club":"Dorking","tiref":"1447345"},{"rank":"46","name":"Finley Dare","time":"18:12.50","date":"27/04/25","club":"Corby","tiref":"1412596"},{"rank":"47","name":"Harry Daykin","time":"18:13.59","date":"16/02/25","club":"Hastings","tiref":"1298113"},{"rank":"48","name":"William Swindlehurst","time":"18:17.34","date":"23/07/25","club":"Nova Cent'n","tiref":"1378722"},{"rank":"49","name":"Ewan Pearce","time":"18:18.52","date":"11/04/25","club":"Nuneaton","tiref":"1345085"},{"rank":"50","name":"William Birchall","time":"18:26.99","date":"04/04/25","club":"TauntonDeane","tiref":"1261240"}],"url":"https://www.swimmingresults.org/12months/last12.php?Pool=L&Stroke=6&Sex=M&AgeGroup=17&date=31%2F01%2F2026&StartNumber=1&RecordsToView=50&Level=N&TargetNationality=E&TargetRegion=P&TargetCounty=XXXX&TargetClub=XXXX"},"expiresAt":1770130306925}